{
"type": "FeatureCollection",
"name": "regional_offices",
"crs": { "type": "name", "properties": { "name": "urn:ogc:def:crs:OGC:1.3:CRS84" } },
"features": [
{ "type": "Feature", "properties": { "office_name": null, "region": null, "address": null, "city": "Boise", "state": null, "zip": null, "phone": "(208) 334-3700 ", "email": null, "hours": "M-F, except state holidays, 8 a.m. to 5 p.m.", "website": null, "full_address": "Boise, ID" }, "geometry": { "type": "Point", "coordinates": [ -116.185853154132005, 43.602049278517697 ] } },
{ "type": "Feature", "properties": { "office_name": null, "region": null, "address": null, "city": "Nampa", "state": null, "zip": null, "phone": "(208) 465-8465 ", "email": null, "hours": "M-F, except state holidays, 8 a.m. to 5 p.m.", "website": "https://idfg.idaho.gov/region/southwest", "full_address": "Nampa, ID" }, "geometry": { "type": "Point", "coordinates": [ -116.504659279161004, 43.603332276483002 ] } }
]
}
